api_cerved/__init__.py
api_cerved/main.py
api_cerved/settings.py
tests/__init__.py
tests/tests.py
api_cerved_tutorial-0.0.2.dist-info/LICENSE
api_cerved_tutorial-0.0.2.dist-info/METADATA
api_cerved_tutorial-0.0.2.dist-info/WHEEL
api_cerved_tutorial-0.0.2.dist-info/top_level.txt
api_cerved_tutorial-0.0.2.dist-info/RECORD
