Metadata-Version: 2.1
Name: api-cerved-tutorial
Version: 0.0.2
Summary: Tutorial for API Cerved.
Home-page: https://github.com/ferromauro/api-cerved-tutorial
Author: Ferro Mauro
Author-email: postmaster@ferromauro.it
License: UNKNOWN
Platform: UNKNOWN
Classifier: Programming Language :: Python :: 3
Classifier: License :: OSI Approved :: MIT License
Classifier: Operating System :: OS Independent
Requires-Python: >=3.6
